bird_tool_utils/__init__.py
bird_tool_utils/argparsing.py
bird_tool_utils/people.py
bird_tool_utils/version.py
bird_tool_utils-0.6.0.dist-info/licenses/LICENCE.txt
bird_tool_utils-0.6.0.dist-info/METADATA
bird_tool_utils-0.6.0.dist-info/WHEEL
bird_tool_utils-0.6.0.dist-info/top_level.txt
bird_tool_utils-0.6.0.dist-info/RECORD
