Metadata-Version: 2.4
Name: bird_tool_utils
Version: 0.6.0
Summary: Python utilities used as part of the bird suite of bioinformatic tools
Author-email: Ben Woodcroft <benjwoodcroft@gmail.com>, Rhys Newell <rhys.newell@hdr.qut.edu.au>
Maintainer-email: Ben Woodcroft <benjwoodcroft@gmail.com>
License-Expression: GPL-3.0-or-later
Project-URL: Homepage, https://github.com/wwood/bird_tool_utils-python/
Keywords: bioinformatics
Classifier: Development Status :: 4 - Beta
Classifier: Topic :: Scientific/Engineering
Classifier: Topic :: Scientific/Engineering :: Bio-Informatics
Classifier: Programming Language :: Python :: 3
Requires-Python: >=3.7
License-File: LICENCE.txt
Requires-Dist: argparse-manpage-birdtools>=1.7.0
Dynamic: license-file
